cognite/ai/__init__.py
cognite/ai/_version.py
cognite/ai/embeddingmodel.py
cognite/ai/pandasai.py
cognite/ai/utils.py
cognite/ai/vectorstore.py
andeplane_ai-0.5.2.dist-info/LICENSE.md
andeplane_ai-0.5.2.dist-info/METADATA
andeplane_ai-0.5.2.dist-info/WHEEL
andeplane_ai-0.5.2.dist-info/RECORD
