Metadata-Version: 2.1
Name: andeplane-ai
Version: 0.5.2
Summary: A set of AI tools for working with Cognite Data Fusion in Python.
License: MIT
Author: Anders Hafreager
Author-email: anders.hafreager@cognite.com
Requires-Python: >=3.9
Classifier: License :: OSI Approved :: MIT License
Classifier: Programming Language :: Python :: 3
Classifier: Programming Language :: Python :: 3.9
Classifier: Programming Language :: Python :: 3.10
Classifier: Programming Language :: Python :: 3.11
Classifier: Programming Language :: Python :: 3.12
Requires-Dist: regex (>=2022.10.31)
